pyutils/__init__.py
pyutils/reminder.py
pyd_utils-1.7.2.dist-info/LICENSE
pyd_utils-1.7.2.dist-info/METADATA
pyd_utils-1.7.2.dist-info/WHEEL
pyd_utils-1.7.2.dist-info/top_level.txt
pyd_utils-1.7.2.dist-info/RECORD
