Metadata-Version: 2.1
Name: pyd-utils
Version: 1.7.2
Summary: pyd-utils
Author: ilkergzlkkr
Author-email: guzelkokarilker@gmail.com
License: UNKNOWN
Platform: UNKNOWN
License-File: LICENSE
Provides-Extra: dev
Requires-Dist: black ; extra == 'dev'
Requires-Dist: pytest ; extra == 'dev'
Requires-Dist: pytest-asyncio ; extra == 'dev'
Requires-Dist: flake8 ; extra == 'dev'
